{
"results": [
{
"name": "NNUG Kristiansand",
"rating": 4.69,
"members": 65
}
],
"meta": {
"lon": "",
"count": 1,
"signed_url": "http://api.meetup.com/2/groups?radius=25.0&order=id&group_urlname=nnug-kristiansand&desc=false&offset=0&format=json&only=name%2Crating%2Cmembers&page=20&fields=&sig_id=97103452&sig=57d1d81038358c39e1bbd42616bab75b04df28c9",
"link": "http://www.meetup.com/2/groups",
"next": "",
"total_count": 1,
"url": "http://www.meetup.com/2/groups?radius=25.0&order=id&group_urlname=nnug-kristiansand&desc=false&offset=0&format=json&only=name%2Crating%2Cmembers&page=20&fields=&sign=true",
"id": "",
"title": "Meetup Groups v2",
"updated": 1370783053000,
"description": """",
"method": "Groups",
"lat": ""
}
}